<?xml version="1.0" encoding="UTF-8"?>
<beans xmlns="http://www.springframework.org/schema/beans"
	xmlns:xsi="http://www.w3.org/2001/XMLSchema-instance"
	xmlns:mvc="http://www.springframework.org/schema/mvc"
	xmlns:context="http://www.springframework.org/schema/context"
	xsi:schemaLocation="http://www.springframework.org/schema/mvc http://www.springframework.org/schema/mvc/spring-mvc-4.3.xsd
		http://www.springframework.org/schema/beans http://www.springframework.org/schema/beans/spring-beans.xsd
		http://www.springframework.org/schema/context http://www.springframework.org/schema/context/spring-context-4.3.xsd">

	<context:component-scan
		base-package="tech.agiledev.spring4.crm.web.rest" />
	<mvc:annotation-driven />

	<!-- this bean must not be lazily initialized if the exporting is to happen -->
	<bean id="exporter"
		class="org.springframework.jmx.export.MBeanExporter" lazy-init="false">
		<property name="beans">
			<map>
				<entry key="bean:name=clientRestEndpoint"
					value-ref="counterBean" />
			</map>
		</property>
		<property name="assembler" ref="assembler" />
	</bean>

	<bean id="jmxAttributeSource"
		class="org.springframework.jmx.export.annotation.AnnotationJmxAttributeSource" />

	<bean id="assembler"
		class="org.springframework.jmx.export.assembler.MetadataMBeanInfoAssembler">
		<property name="attributeSource" ref="jmxAttributeSource" />
	</bean>

	<bean id="counterBean"
		class="tech.agiledev.spring4.crm.jmx.OperationCounter" />
</beans>
